<?xml version="1.0" encoding="windows-1255"?>
	<STORE URL="" DATE="" NAME="" STATUS="" ID="">
	<PRODUCTS>
<PRODUCT>
			<PRODUCT_URL>http://www.elecom.co.il/product_info.php?products_id=2270</PRODUCT_URL>
			<PRODUCT_NAME>מתקן תליה זרוע LCD מפרקית מקצועית למסך 15עד 32 אינץ - C-502 חזק ומקצועי</PRODUCT_NAME>
			<MODEL></MODEL>
			<DETAILS>מפרט:

מתקן תלייה אוניברסלי למסכי LCD ופלאזמה בגודל &quot;15 -&quot;37     
 
  2 זרועות/ 3 מפרקים לכיוון זווית צפיה אופטימלית
 
 כיווני זווית צפיה ימינה-שמאלה ו- מעלה-מטה מתאים לתליה על קיר גבס התקנה קלה ופשוטה.

 פתיחת זרועות מקסימלית: 8 - 49 ס&quot;מ מהקיר לנוחות מושלמת בסיבוב המסך לצדדים

  קדחים מובנים בזרועות תליה המאפשרים את כיוון גובה המסך

  פלס מובנה להתקנה ישרה ונוחה 

 מתאים לתליה על קיר גבס

  מצורף סט עם מבחר  ברגים  המתאימים לרוב סוגי המסכים.</DETAILS>
			<CURRENCY>"ILS"</CURRENCY>
			<PRICE>179.0000</PRICE>
			<SHIPMENT_COST>0.00</SHIPMENT_COST>
			<DELIVERY_TIME>עד 7 ימי עבודה</DELIVERY_TIME>
			<MANUFACTURER>Lexus</MANUFACTURER>
			<WARRANTY></WARRANTY>
			<IMAGE>http://www.elecom.co.il/images/מתקן תלייה.jpg</IMAGE>
			</PRODUCT>
</PRODUCTS>
	</STORE>